acemeta/Console.py
acemeta/Discord.py
acemeta/Files.py
acemeta/GitHub.py
acemeta/Minecraft.py
acemeta/Numbers.py
acemeta/Stochastics.py
acemeta/__init__.py
workflows/Discord.py
workflows/GitHub.py
workflows/__init__.py
workflows/files.py
workflows.py-0.0.0.dist-info/LICENSE
workflows.py-0.0.0.dist-info/METADATA
workflows.py-0.0.0.dist-info/WHEEL
workflows.py-0.0.0.dist-info/top_level.txt
workflows.py-0.0.0.dist-info/RECORD
