Metadata-Version: 2.1
Name: workflows.py
Version: 0.0.0
Summary: Library for typical workflows
Author: Annhilati
License-File: LICENSE
Requires-Dist: requests
